agentbox/__init__.py
agentbox_ai-0.0.2.dist-info/METADATA
agentbox_ai-0.0.2.dist-info/WHEEL
agentbox_ai-0.0.2.dist-info/top_level.txt
agentbox_ai-0.0.2.dist-info/RECORD
